duckling_chinese/__init__.py
duckling_chinese/dimension.py
duckling_chinese/ranker.py
duckling_chinese/utils.py
duckling_chinese/jars/aho-corasick-double-array-trie-1.2.3.jar
duckling_chinese/jars/checker-qual-3.8.0.jar
duckling_chinese/jars/commons-io-2.11.0.jar
duckling_chinese/jars/commons-lang3-3.12.0.jar
duckling_chinese/jars/commons-text-1.10.0.jar
duckling_chinese/jars/config-1.3.4.jar
duckling_chinese/jars/duckling-core_2.13-1.6.4.4.jar
duckling_chinese/jars/easy-bert-1.0.3.jar
duckling_chinese/jars/emoji-java-5.1.1.jar
duckling_chinese/jars/error_prone_annotations-2.5.1.jar
duckling_chinese/jars/failureaccess-1.0.1.jar
duckling_chinese/jars/guava-30.1.1-jre.jar
duckling_chinese/jars/j2objc-annotations-1.3.jar
duckling_chinese/jars/jackson-annotations-2.9.10.jar
duckling_chinese/jars/jackson-core-2.9.10.jar
duckling_chinese/jars/jackson-databind-2.9.10.8.jar
duckling_chinese/jars/json-20170516.jar
duckling_chinese/jars/json4s-ast_2.13-3.6.12.jar
duckling_chinese/jars/json4s-core_2.13-3.6.12.jar
duckling_chinese/jars/json4s-jackson_2.13-3.6.12.jar
duckling_chinese/jars/json4s-scalap_2.13-3.6.12.jar
duckling_chinese/jars/jsr305-3.0.2.jar
duckling_chinese/jars/kryo5-5.3.0.jar
duckling_chinese/jars/listenablefuture-9999.0-empty-to-avoid-conflict-with-guava.jar
duckling_chinese/jars/lunar-1.5.jar
duckling_chinese/jars/paranamer-2.8.jar
duckling_chinese/jars/scala-java8-compat_2.13-1.0.2.jar
duckling_chinese/jars/scala-library-2.13.10.jar
duckling_chinese/jars/scala-logging_2.13-3.9.5.jar
duckling_chinese/jars/scala-reflect-2.13.8.jar
duckling_chinese/jars/scalaz-core_2.13-7.2.27.jar
duckling_chinese/jars/slf4j-api-1.7.26.jar
duckling_chinese-1.1.8.dist-info/licenses/LICENSE
duckling_chinese-1.1.8.dist-info/METADATA
duckling_chinese-1.1.8.dist-info/WHEEL
duckling_chinese-1.1.8.dist-info/top_level.txt
duckling_chinese-1.1.8.dist-info/RECORD
