Metadata-Version: 2.4
Name: duckling_chinese
Version: 1.1.8
Summary: Ducking Chinese
Author-email: 范叶亮 <leo-van@hotmail.com>
Project-URL: homepage, https://github.com/leovan/duckling-chinese
Project-URL: documentation, https://duckling.leovan.tech
Keywords: duckling,chinese,nlp
Classifier: Development Status :: 5 - Production/Stable
Classifier: Intended Audience :: Science/Research
Classifier: Intended Audience :: Developers
Classifier: License :: OSI Approved :: MIT License
Classifier: Operating System :: MacOS :: MacOS X
Classifier: Operating System :: Microsoft :: Windows
Classifier: Operating System :: Unix
Classifier: Programming Language :: Java
Classifier: Programming Language :: Python :: 3
Classifier: Programming Language :: Python :: 3 :: Only
Classifier: Topic :: Software Development :: Libraries
Classifier: Topic :: Scientific/Engineering
Requires-Python: >=3.6
License-File: LICENSE
Requires-Dist: Jpype1
Requires-Dist: backports.zoneinfo; python_version < "3.9"
Dynamic: license-file
